.gitignore
CHANGELOG.md
LICENSE
PKG-INFO
README.md
pyproject.toml
.github/pull_request_template.md
.github/ISSUE_TEMPLATE/bug_report.yml
.github/ISSUE_TEMPLATE/documentation_update.md
.github/ISSUE_TEMPLATE/feature_request.md
.github/workflows/check_pr.yml
.github/workflows/ci.yml
.github/workflows/semantic_release.yml
qtmonaco/__init__.py
qtmonaco/connector.py
qtmonaco/monaco.py
qtmonaco/monaco_page.py
qtmonaco/pylsp_provider.py
qtmonaco/resource_loader.py
qtmonaco/js_build/index.html
qtmonaco/js_build/assets/codicon.ttf
qtmonaco/js_build/assets/index.css
qtmonaco/js_build/assets/index.js
qtmonaco/js_build/assets/monaco-core.css
qtmonaco/js_build/assets/monaco-core.js
qtmonaco/js_build/assets/vendor.js
qtmonaco/js_build/monacoeditorwork/css.worker.bundle.js
qtmonaco/js_build/monacoeditorwork/editor.worker.bundle.js
qtmonaco/js_build/monacoeditorwork/html.worker.bundle.js
qtmonaco/js_build/monacoeditorwork/json.worker.bundle.js
qtmonaco/js_build/monacoeditorwork/ts.worker.bundle.js
qtmonaco-0.8.1.dist-info/METADATA
qtmonaco-0.8.1.dist-info/WHEEL
qtmonaco-0.8.1.dist-info/licenses/LICENSE
qtmonaco-0.8.1.dist-info/RECORD
